{
    "contenido": [
        {
            "imagen": "imagenes/Peeling_químico.jpg",
            "titulo": "¿Qué hacemos?",
            "descripcion": "¡Bienvenido a nuestra clínica de estética médica! Nos enorgullece ofrecer una amplia variedad de tratamientos estéticos médicos para ayudarte a sentirte seguro y radiante en tu propia piel. Nuestro equipo de profesionales altamente capacitados se dedica a ofrecer tratamientos personalizados y de alta calidad para satisfacer tus necesidades y objetivos individuales de belleza. Nos enfocamos en escuchar tus inquietudes y metas de belleza, y trabajamos contigo para crear un plan de tratamiento efectivo y personalizado. Ofrecemos tratamientos innovadores y avanzados que están diseñados para mejorar la apariencia de la piel, reducir la celulitis, eliminar el vello no deseado y más. Desde tratamientos de inyecciones faciales hasta procedimientos corporales no invasivos, estamos comprometidos con brindarte resultados notables y duraderos. En nuestra clínica, nos tomamos muy en serio la seguridad y la comodidad de nuestros pacientes. Utilizamos solo los productos y equipos más avanzados y de alta calidad para asegurarnos de que nuestros pacientes reciban los mejores tratamientos estéticos médicos posibles en un entorno seguro y relajado. Nos esforzamos por ser líderes en la industria de la estética médica, y estamos dedicados a mantenerte informado sobre los últimos avances en la industria. Nuestra misión es ayudarte a sentirte y lucir lo mejor posible, y estamos comprometidos a lograr tus objetivos de belleza de manera segura y efectiva."
        }
    ],
    "items": [
        {
            "img": "imagenes/tratamiento_destacado.jpg",
            "text": "Tratamiento Destacado",
            "destiny": "treatment.html"
        },
        {
            "img": "imagenes/pida_cita.jpg",
            "text": "Pida Cita",
            "destiny": "contactUs.html"
        },
        {
            "img": "imagenes/promociones.jpg",
            "text": "Promociones",
            "destiny": "promotions.html"
        }
    ]
}